Metadata-Version: 2.4
Name: llama-index-vector-stores-deeplake
Version: 0.4.1
Summary: llama-index vector_stores deeplake integration
Author-email: Activeloop <support@activeloop.ai>
License-Expression: MIT
License-File: LICENSE
Requires-Python: <4.0,>=3.9
Requires-Dist: deeplake>=3.9.12
Requires-Dist: llama-index-core<0.15,>=0.13.0
Requires-Dist: pyjwt
